pyocmf/__init__.py
pyocmf/cli/__init__.py
pyocmf/cli/app.py
pyocmf/cli/commands.py
pyocmf/cli/display.py
pyocmf/cli/utils.py
pyocmf/compliance/__init__.py
pyocmf/compliance/models.py
pyocmf/compliance/reading.py
pyocmf/compliance/transaction.py
pyocmf/constants.py
pyocmf/core/__init__.py
pyocmf/core/ocmf.py
pyocmf/core/payload.py
pyocmf/core/reading.py
pyocmf/core/signature.py
pyocmf/crypto/__init__.py
pyocmf/crypto/availability.py
pyocmf/crypto/verification.py
pyocmf/enums/__init__.py
pyocmf/enums/crypto.py
pyocmf/enums/identifiers.py
pyocmf/enums/reading.py
pyocmf/enums/units.py
pyocmf/exceptions.py
pyocmf/models/__init__.py
pyocmf/models/cable_loss.py
pyocmf/models/obis.py
pyocmf/models/public_key.py
pyocmf/models/timestamp.py
pyocmf/py.typed
pyocmf/registries/__init__.py
pyocmf/registries/obis.py
pyocmf/types/__init__.py
pyocmf/types/encoding.py
pyocmf/types/identifiers.py
pyocmf/utils/__init__.py
pyocmf/utils/xml.py
pyocmf-0.2.2.dist-info/WHEEL
pyocmf-0.2.2.dist-info/entry_points.txt
pyocmf-0.2.2.dist-info/METADATA
pyocmf-0.2.2.dist-info/RECORD
