Metadata-Version: 2.3
Name: pyocmf
Version: 0.2.2
Summary: Python library for parsing and verifying OCMF (Open Charge Metering Format) signatures from electric vehicle charging stations
Keywords: ocmf,ev,charging,metering,electric-vehicle,signature-verification,eichrecht
Author: Paul Wullenweber
Author-email: Paul Wullenweber <44506902+paul-ww@users.noreply.github.com>
License: MIT
Classifier: Development Status :: 4 - Beta
Classifier: Intended Audience :: Developers
Classifier: License :: OSI Approved :: MIT License
Classifier: Programming Language :: Python :: 3
Classifier: Programming Language :: Python :: 3.11
Classifier: Programming Language :: Python :: 3.12
Classifier: Programming Language :: Python :: 3.13
Classifier: Topic :: Software Development :: Libraries :: Python Modules
Classifier: Topic :: Utilities
Requires-Dist: phonenumbers~=9.0
Requires-Dist: pydantic-extra-types~=2.10
Requires-Dist: pydantic~=2.10
Requires-Dist: pyocmf[cli,crypto] ; extra == 'all'
Requires-Dist: rich~=14.2.0 ; extra == 'cli'
Requires-Dist: typer~=0.20.0 ; extra == 'cli'
Requires-Dist: cryptography~=44.0 ; extra == 'crypto'
Requires-Python: >=3.11
Project-URL: Homepage, https://github.com/paul-ww/pyocmf
Project-URL: Documentation, https://paul-ww.github.io/pyocmf/
Project-URL: Repository, https://github.com/paul-ww/pyocmf
Project-URL: Issues, https://github.com/paul-ww/pyocmf/issues
Provides-Extra: all
Provides-Extra: cli
Provides-Extra: crypto
